tensorus/__init__.py
tensorus/agent_orchestrator.py
tensorus/api.py
tensorus/audit.py
tensorus/automl_agent.py
tensorus/base.py
tensorus/cli.py
tensorus/compression.py
tensorus/config.py
tensorus/dummy_env.py
tensorus/embedding_agent.py
tensorus/financial_data_generator.py
tensorus/hybrid_search.py
tensorus/indexing.py
tensorus/ingestion_agent.py
tensorus/llm_parser.py
tensorus/nql_agent.py
tensorus/operation_history.py
tensorus/rl_agent.py
tensorus/sdk.py
tensorus/storage_ops.py
tensorus/storage_ops_with_history.py
tensorus/tensor_chunking.py
tensorus/tensor_chunking_enhanced.py
tensorus/tensor_decompositions.py
tensorus/tensor_ops.py
tensorus/tensor_storage.py
tensorus/time_series_predictor.py
tensorus/utils.py
tensorus/vector_database.py
tensorus/api/__init__.py
tensorus/api/dependencies.py
tensorus/api/endpoints.py
tensorus/api/models.py
tensorus/api/security.py
tensorus/api/routers/__init__.py
tensorus/api/routers/operations.py
tensorus/api/routers/query.py
tensorus/api/routers/vector.py
tensorus/auth/__init__.py
tensorus/auth/key_generator.py
tensorus/metadata/__init__.py
tensorus/metadata/index_manager.py
tensorus/metadata/index_persistence.py
tensorus/metadata/indexing.py
tensorus/metadata/postgres_storage.py
tensorus/metadata/schemas.py
tensorus/metadata/schemas_iodata.py
tensorus/metadata/storage.py
tensorus/metadata/storage_abc.py
tensorus/storage/__init__.py
tensorus/storage/connectors.py
tensorus-0.1.0.dist-info/licenses/LICENSE
tensorus-0.1.0.dist-info/METADATA
tensorus-0.1.0.dist-info/WHEEL
tensorus-0.1.0.dist-info/entry_points.txt
tensorus-0.1.0.dist-info/top_level.txt
tensorus-0.1.0.dist-info/RECORD
