Metadata-Version: 2.4
Name: tensorus
Version: 0.1.0
Summary: An agentic tensor database with unified SDK, agent orchestration, and intelligent workflows for ML/AI applications.
Author-email: Tensorus Team <ai@tensorus.com>
License: MIT License
Project-URL: Homepage, https://tensorus.com
Project-URL: Repository, https://github.com/tensorus/tensorus
Keywords: tensor,database,agent,ai,pytorch,fastapi,streamlit,automl,reinforcement-learning,data-ingestion
Classifier: Development Status :: 3 - Alpha
Classifier: Intended Audience :: Developers
Classifier: Intended Audience :: Science/Research
Classifier: License :: OSI Approved :: MIT License
Classifier: Operating System :: OS Independent
Classifier: Programming Language :: Python :: 3.10
Classifier: Programming Language :: Python :: 3.11
Classifier: Topic :: Database
Classifier: Topic :: Scientific/Engineering :: Artificial Intelligence
Classifier: Topic :: Software Development :: Libraries
Requires-Python: >=3.10
License-File: LICENSE
Provides-Extra: models
Requires-Dist: tensorus-models>=0.0.3; extra == "models"
Dynamic: license-file
